LICENSE
MANIFEST.in
README.md
VERSION
setup.py
sentry_taiga/.DS_Store
sentry_taiga/__init__.py
sentry_taiga/plugin.py
sentry_taiga.egg-info/PKG-INFO
sentry_taiga.egg-info/SOURCES.txt
sentry_taiga.egg-info/dependency_links.txt
sentry_taiga.egg-info/entry_points.txt
sentry_taiga.egg-info/requires.txt
sentry_taiga.egg-info/top_level.txt
sentry_taiga.egg-info/zip-safe