Metadata-Version: 1.1
Name: sentry-taiga
Version: 0.1.4
Summary: A Sentry extension which integrates with Taiga.
Home-page: http://github.com/rochsystems/sentry-taiga
Author: RochSystems LLC
Author-email: jordi.llonch@rochsystems.com
License: MIT
Platform: UNKNOWN
Classifier: Framework :: Django
Classifier: Intended Audience :: Developers
Classifier: Intended Audience :: System Administrators
Classifier: Operating System :: OS Independent
Classifier: Topic :: Software Development
